arcade_customerio_api/__init__.py
arcade_customerio_api/moar/Customerio.json
arcade_customerio_api/moar/openapi.json
arcade_customerio_api/tools/__init__.py
arcade_customerio_api/tools/request_body_schemas.py
arcade_customerio_api/wrapper_tools/CheckEmailSuppression.json
arcade_customerio_api/wrapper_tools/CreateManualSegment.json
arcade_customerio_api/wrapper_tools/CreateNewCollection.json
arcade_customerio_api/wrapper_tools/CreateWebhook.json
arcade_customerio_api/wrapper_tools/DeleteCollection.json
arcade_customerio_api/wrapper_tools/DeleteManualSegment.json
arcade_customerio_api/wrapper_tools/DeleteNewsletter.json
arcade_customerio_api/wrapper_tools/DeleteReportingWebhook.json
arcade_customerio_api/wrapper_tools/DownloadExportSignedLink.json
arcade_customerio_api/wrapper_tools/ExportCustomerData.json
arcade_customerio_api/wrapper_tools/ExportDeliveryData.json
arcade_customerio_api/wrapper_tools/FetchMessageDeliveries.json
arcade_customerio_api/wrapper_tools/FilterPeopleInWorkspace.json
arcade_customerio_api/wrapper_tools/FindSegmentDependencies.json
arcade_customerio_api/wrapper_tools/FindSuppressedEmailAddresses.json
arcade_customerio_api/wrapper_tools/FindWorkspaceObjects.json
arcade_customerio_api/wrapper_tools/GetAllSegments.json
arcade_customerio_api/wrapper_tools/GetAllowlistIps.json
arcade_customerio_api/wrapper_tools/GetArchivedMessage.json
arcade_customerio_api/wrapper_tools/GetBroadcastActionInfo.json
arcade_customerio_api/wrapper_tools/GetBroadcastActionLinkMetrics.json
arcade_customerio_api/wrapper_tools/GetBroadcastActionMetrics.json
arcade_customerio_api/wrapper_tools/GetBroadcastActions.json
arcade_customerio_api/wrapper_tools/GetBroadcastErrors.json
arcade_customerio_api/wrapper_tools/GetBroadcastLinkMetrics.json
arcade_customerio_api/wrapper_tools/GetBroadcastMessageInfo.json
arcade_customerio_api/wrapper_tools/GetBroadcastMetadata.json
arcade_customerio_api/wrapper_tools/GetBroadcastMetrics.json
arcade_customerio_api-1.0.0.dist-info/METADATA
arcade_customerio_api-1.0.0.dist-info/WHEEL
arcade_customerio_api-1.0.0.dist-info/entry_points.txt
arcade_customerio_api-1.0.0.dist-info/licenses/LICENSE
arcade_customerio_api-1.0.0.dist-info/RECORD
